{"filters":{"dateFrom":"2025-08-31","dateTo":"2025-09-01","permission":"TIER_ONE"},"resultSet":{"count":36,"competitions":"BSA,DED,PL,FL1,BL1,PPL,PD,SA","first":"2025-08-31","last":"2025-08-31","played":1},"matches":[{"area":{"id":2032,"name":"Brazil","code":"BRA","flag":"https://crests.football-data.org/764.svg"},"competition":{"id":2013,"name":"Campeonato Brasileiro Série A","code":"BSA","type":"LEAGUE","emblem":"https://crests.football-data.org/bsa.png"},"season":{"id":2371,"startDate":"2025-03-29","endDate":"2025-12-21","currentMatchday":22,"winner":null},"id":535150,"utcDate":"2025-08-31T00:00:00Z","status":"FINISHED","matchday":22,"stage":"REGULAR_SEASON","group":null,"lastUpdated":"2025-08-31T02:05:17Z","homeTeam":{"id":1771,"name":"Cruzeiro EC","shortName":"Cruzeiro","tla":"CRU","crest":"https://crests.football-data.org/1771.png"},"awayTeam":{"id":1776,"name":"São Paulo FC","shortName":"São Paulo","tla":"PAU","crest":"https://crests.football-data.org/1776.png"},"score":{"winner":"HOME_TEAM","duration":"REGULAR","fullTime":{"home":1,"away":0},"halfTime":{"home":0,"away":0},"regularTime":{"home":0,"away":0},"extraTime":{"home":0,"away":0},"penalties":{"home":0,"away":0}},"odds":{"msg":"Activate Odds-Package in User-Panel to retrieve odds."},"referees":[]},{"area":{"id":2163,"name":"Netherlands","code":"NLD","flag":"https://crests.football-data.org/8601.svg"},"competition":{"id":2003,"name":"Eredivisie","code":"DED","type":"LEAGUE","emblem":"https://crests.football-data.org/ED.png"},"season":{"id":2400,"startDate":"2025-08-08","endDate":"2026-05-17","currentMatchday":4,"winner":null},"id":537473,"utcDate":"2025-08-31T10:15:00Z","status":"TIMED","matchday":4,"stage":"REGULAR_SEASON","group":null,"lastUpdated":"2025-08-31T01:32:00Z","homeTeam":{"id":1920,"name":"Fortuna Sittard","shortName":"Sittard","tla":"SIT","crest":"https://crests.football-data.org/1920.png"},"awayTeam":{"id":1915,"name":"NEC","shortName":"NEC","tla":"NEC","crest":"https://crests.football-data.org/1915.png"},"score":{"winner":null,"duration":"REGULAR","fullTime":{"home":null,"away":null},"halfTime":{"home":null,"away":null}},"odds":{"msg":"Activate Odds-Package in User-Panel to retrieve odds."},"referees":[{"id":56917,"name":"Erwin Blank","type":"REFEREE","nationality":"Netherlands"}]},{"area":{"id":2163,"name":"Netherlands","code":"NLD","flag":"https://crests.football-data.org/8601.svg"},"competition":{"id":2003,"name":"Eredivisie","code":"DED","type":"LEAGUE","emblem":"https://crests.football-data.org/ED.png"},"season":{"id":2400,"startDate":"2025-08-08","endDate":"2026-05-17","currentMatchday":4,"winner":null},"id":537474,"utcDate":"2025-08-31T12:30:00Z","status":"TIMED","matchday":4,"stage":"REGULAR_SEASON","group":null,"lastUpdated":"2025-08-25T01:32:05Z","homeTeam":{"id":684,"name":"PEC Zwolle","shortName":"Zwolle","tla":"ZWO","crest":"https://crests.football-data.org/684.png"},"awayTeam":{"id":676,"name":"FC Utrecht","shortName":"Utrecht","tla":"UTR","crest":"https://crests.football-data.org/676.png"},"score":{"winner":null,"duration":"REGULAR","fullTime":{"home":null,"away":null},"halfTime":{"home":null,"away":null}},"odds":{"msg":"Activate Odds-Package in User-Panel to retrieve odds."},"referees":[]},{"area":{"id":2163,"name":"Netherlands","code":"NLD","flag":"https://crests.football-data.org/8601.svg"},"competition":{"id":2003,"name":"Eredivisie","code":"DED","type":"LEAGUE","emblem":"https://crests.football-data.org/ED.png"},"season":{"id":2400,"startDate":"2025-08-08","endDate":"2026-05-17","currentMatchday":4,"winner":null},"id":537475,"utcDate":"2025-08-31T12:30:00Z","status":"TIMED","matchday":4,"stage":"REGULAR_SEASON","group":null,"lastUpdated":"2025-08-30T01:32:02Z","homeTeam":{"id":6806,"name":"Sparta Rotterdam","shortName":"Sparta","tla":"SPA","crest":"https://crests.football-data.org/6806.png"},"awayTeam":{"id":675,"name":"Feyenoord Rotterdam","shortName":"Feyenoord","tla":"FEY","crest":"https://crests.football-data.org/675.png"},"score":{"winner":null,"duration":"REGULAR","fullTime":{"home":null,"away":null},"halfTime":{"home":null,"away":null}},"odds":{"msg":"Activate Odds-Package in User-Panel to retrieve odds."},"referees":[]},{"area":{"id":2072,"name":"England","code":"ENG","flag":"https://crests.football-data.org/770.svg"},"competition":{"id":2021,"name":"Premier League","code":"PL","type":"LEAGUE","emblem":"https://crests.football-data.org/PL.png"},"season":{"id":2403,"startDate":"2025-08-15","endDate":"2026-05-24","currentMatchday":3,"winner":null},"id":537807,"utcDate":"2025-08-31T13:00:00Z","status":"TIMED","matchday":3,"stage":"REGULAR_SEASON","group":null,"lastUpdated":"2025-08-31T01:32:00Z","homeTeam":{"id":397,"name":"Brighton & Hove Albion FC","shortName":"Brighton Hove","tla":"BHA","crest":"https://crests.football-data.org/397.png"},"awayTeam":{"id":65,"name":"Manchester City FC","shortName":"Man City","tla":"MCI","crest":"https://crests.football-data.org/65.png"},"score":{"winner":null,"duration":"REGULAR","fullTime":{"home":null,"away":null},"halfTime":{"home":null,"away":null}},"odds":{"msg":"Activate Odds-Package in User-Panel to retrieve odds."},"referees":[]},{"area":{"id":2072,"name":"England","code":"ENG","flag":"https://crests.football-data.org/770.svg"},"competition":{"id":2021,"name":"Premier League","code":"PL","type":"LEAGUE","emblem":"https://crests.football-data.org/PL.png"},"season":{"id":2403,"startDate":"2025-08-15","endDate":"2026-05-24","currentMatchday":3,"winner":null},"id":537812,"utcDate":"2025-08-31T13:00:00Z","status":"TIMED","matchday":3,"stage":"REGULAR_SEASON","group":null,"lastUpdated":"2025-08-31T01:32:00Z","homeTeam":{"id":351,"name":"Nottingham Forest FC","shortName":"Nottingham","tla":"NOT","crest":"https://crests.football-data.org/351.png"},"awayTeam":{"id":563,"name":"West Ham United FC","shortName":"West Ham","tla":"WHU","crest":"https://crests.football-data.org/563.png"},"score":{"winner":null,"duration":"REGULAR","fullTime":{"home":null,"away":null},"halfTime":{"home":null,"away":null}},"odds":{"msg":"Activate Odds-Package in User-Panel to retrieve odds."},"referees":[]},{"area":{"id":2081,"name":"France","code":"FRA","flag":"https://crests.football-data.org/773.svg"},"competition":{"id":2015,"name":"Ligue 1","code":"FL1","type":"LEAGUE","emblem":"https://crests.football-data.org/FL1.png"},"season":{"id":2420,"startDate":"2025-08-17","endDate":"2026-05-16","currentMatchday":3,"winner":null},"id":542432,"utcDate":"2025-08-31T13:00:00Z","status":"TIMED","matchday":3,"stage":"REGULAR_SEASON","group":null,"lastUpdated":"2025-08-31T01:32:00Z","homeTeam":{"id":532,"name":"Angers SCO","shortName":"Angers SCO","tla":"ANG","crest":"https://crests.football-data.org/532.png"},"awayTeam":{"id":529,"name":"Stade Rennais FC 1901","shortName":"Stade Rennais","tla":"REN","crest":"https://crests.football-data.org/529.png"},"score":{"winner":null,"duration":"REGULAR","fullTime":{"home":null,"away":null},"halfTime":{"home":null,"away":null}},"odds":{"msg":"Activate Odds-Package in User-Panel to retrieve odds."},"referees":[]},{"area":{"id":2088,"name":"Germany","code":"DEU","flag":"https://crests.football-data.org/759.svg"},"competition":{"id":2002,"name":"Bundesliga","code":"BL1","type":"LEAGUE","emblem":"https://crests.football-data.org/BL1.png"},"season":{"id":2414,"startDate":"2025-08-22","endDate":"2026-05-16","currentMatchday":2,"winner":null},"id":540419,"utcDate":"2025-08-31T13:30:00Z","status":"TIMED","matchday":2,"stage":"REGULAR_SEASON","group":null,"lastUpdated":"2025-08-31T01:32:00Z","homeTeam":{"id":11,"name":"VfL Wolfsburg","shortName":"Wolfsburg","tla":"WOB","crest":"https://crests.football-data.org/11.png"},"awayTeam":{"id":15,"name":"1. FSV Mainz 05","shortName":"Mainz","tla":"M05","crest":"https://crests.football-data.org/15.png"},"score":{"winner":null,"duration":"REGULAR","fullTime":{"home":null,"away":null},"halfTime":{"home":null,"away":null}},"odds":{"msg":"Activate Odds-Package in User-Panel to retrieve odds."},"referees":[]},{"area":{"id":2187,"name":"Portugal","code":"POR","flag":"https://crests.football-data.org/765.svg"},"competition":{"id":2017,"name":"Primeira Liga","code":"PPL","type":"LEAGUE","emblem":"https://crests.football-data.org/PPL.png"},"season":{"id":2433,"startDate":"2025-08-08","endDate":"2026-05-17","currentMatchday":4,"winner":null},"id":545732,"utcDate":"2025-08-31T14:30:00Z","status":"TIMED","matchday":4,"stage":"REGULAR_SEASON","group":null,"lastUpdated":"2025-08-31T01:32:00Z","homeTeam":{"id":1049,"name":"CD Tondela","shortName":"Tondela","tla":"TON","crest":"https://crests.football-data.org/1049.png"},"awayTeam":{"id":582,"name":"GD Estoril Praia","shortName":"Estoril Praia","tla":"EST","crest":"https://crests.football-data.org/582.png"},"score":{"winner":null,"duration":"REGULAR","fullTime":{"home":null,"away":null},"halfTime":{"home":null,"away":null}},"odds":{"msg":"Activate Odds-Package in User-Panel to retrieve odds."},"referees":[]},{"area":{"id":2163,"name":"Netherlands","code":"NLD","flag":"https://crests.football-data.org/8601.svg"},"competition":{"id":2003,"name":"Eredivisie","code":"DED","type":"LEAGUE","emblem":"https://crests.football-data.org/ED.png"},"season":{"id":2400,"startDate":"2025-08-08","endDate":"2026-05-17","currentMatchday":4,"winner":null},"id":537476,"utcDate":"2025-08-31T14:45:00Z","status":"TIMED","matchday":4,"stage":"REGULAR_SEASON","group":null,"lastUpdated":"2025-08-31T01:32:00Z","homeTeam":{"id":681,"name":"NAC Breda","shortName":"NAC","tla":"NAC","crest":"https://crests.football-data.org/681.png"},"awayTeam":{"id":682,"name":"AZ","shortName":"AZ","tla":"AZ","crest":"https://crests.football-data.org/682.png"},"score":{"winner":null,"duration":"REGULAR","fullTime":{"home":null,"away":null},"halfTime":{"home":null,"away":null}},"odds":{"msg":"Activate Odds-Package in User-Panel to retrieve odds."},"referees":[]},{"area":{"id":2224,"name":"Spain","code":"ESP","flag":"https://crests.football-data.org/760.svg"},"competition":{"id":2014,"name":"Primera Division","code":"PD","type":"LEAGUE","emblem":"https://crests.football-data.org/laliga.png"},"season":{"id":2429,"startDate":"2025-08-17","endDate":"2026-05-24","currentMatchday":6,"winner":null},"id":544232,"utcDate":"2025-08-31T15:00:00Z","status":"TIMED","matchday":3,"stage":"REGULAR_SEASON","group":null,"lastUpdated":"2025-08-31T01:32:00Z","homeTeam":{"id":558,"name":"RC Celta de Vigo","shortName":"Celta","tla":"CEL","crest":"https://crests.football-data.org/558.png"},"awayTeam":{"id":94,"name":"Villarreal CF","shortName":"Villarreal","tla":"VIL","crest":"https://crests.football-data.org/94.png"},"score":{"winner":null,"duration":"REGULAR","fullTime":{"home":null,"away":null},"halfTime":{"home":null,"away":null}},"odds":{"msg":"Activate Odds-Package in User-Panel to retrieve odds."},"referees":[]},{"area":{"id":2081,"name":"France","code":"FRA","flag":"https://crests.football-data.org/773.svg"},"competition":{"id":2015,"name":"Ligue 1","code":"FL1","type":"LEAGUE","emblem":"https://crests.football-data.org/FL1.png"},"season":{"id":2420,"startDate":"2025-08-17","endDate":"2026-05-16","currentMatchday":3,"winner":null},"id":542424,"utcDate":"2025-08-31T15:15:00Z","status":"TIMED","matchday":3,"stage":"REGULAR_SEASON","group":null,"lastUpdated":"2025-08-31T01:32:00Z","homeTeam":{"id":533,"name":"Le Havre AC","shortName":"Le Havre","tla":"HAC","crest":"https://crests.football-data.org/533.png"},"awayTeam":{"id":522,"name":"OGC Nice","shortName":"Nice","tla":"NIC","crest":"https://crests.football-data.org/522.png"},"score":{"winner":null,"duration":"REGULAR","fullTime":{"home":null,"away":null},"halfTime":{"home":null,"away":null}},"odds":{"msg":"Activate Odds-Package in User-Panel to retrieve odds."},"referees":[]},{"area":{"id":2081,"name":"France","code":"FRA","flag":"https://crests.football-data.org/773.svg"},"competition":{"id":2015,"name":"Ligue 1","code":"FL1","type":"LEAGUE","emblem":"https://crests.football-data.org/FL1.png"},"season":{"id":2420,"startDate":"2025-08-17","endDate":"2026-05-16","currentMatchday":3,"winner":null},"id":542425,"utcDate":"2025-08-31T15:15:00Z","status":"TIMED","matchday":3,"stage":"REGULAR_SEASON","group":null,"lastUpdated":"2025-08-31T01:32:00Z","homeTeam":{"id":548,"name":"AS Monaco FC","shortName":"Monaco","tla":"ASM","crest":"https://crests.football-data.org/548.png"},"awayTeam":{"id":576,"name":"RC Strasbourg Alsace","shortName":"Strasbourg","tla":"RC ","crest":"https://crests.football-data.org/576.png"},"score":{"winner":null,"duration":"REGULAR","fullTime":{"home":null,"away":null},"halfTime":{"home":null,"away":null}},"odds":{"msg":"Activate Odds-Package in User-Panel to retrieve odds."},"referees":[]},{"area":{"id":2081,"name":"France","code":"FRA","flag":"https://crests.football-data.org/773.svg"},"competition":{"id":2015,"name":"Ligue 1","code":"FL1","type":"LEAGUE","emblem":"https://crests.football-data.org/FL1.png"},"season":{"id":2420,"startDate":"2025-08-17","endDate":"2026-05-16","currentMatchday":3,"winner":null},"id":542428,"utcDate":"2025-08-31T15:15:00Z","status":"TIMED","matchday":3,"stage":"REGULAR_SEASON","group":null,"lastUpdated":"2025-08-25T01:32:05Z","homeTeam":{"id":1045,"name":"Paris FC","shortName":"Paris FC","tla":"PFC","crest":"https://crests.football-data.org/1045.png"},"awayTeam":{"id":545,"name":"FC Metz","shortName":"FC Metz","tla":"FCM","crest":"https://crests.football-data.org/545.png"},"score":{"winner":null,"duration":"REGULAR","fullTime":{"home":null,"away":null},"halfTime":{"home":null,"away":null}},"odds":{"msg":"Activate Odds-Package in User-Panel to retrieve odds."},"referees":[]},{"area":{"id":2072,"name":"England","code":"ENG","flag":"https://crests.football-data.org/770.svg"},"competition":{"id":2021,"name":"Premier League","code":"PL","type":"LEAGUE","emblem":"https://crests.football-data.org/PL.png"},"season":{"id":2403,"startDate":"2025-08-15","endDate":"2026-05-24","currentMatchday":3,"winner":null},"id":537809,"utcDate":"2025-08-31T15:30:00Z","status":"TIMED","matchday":3,"stage":"REGULAR_SEASON","group":null,"lastUpdated":"2025-08-31T01:32:00Z","homeTeam":{"id":64,"name":"Liverpool FC","shortName":"Liverpool","tla":"LIV","crest":"https://crests.football-data.org/64.png"},"awayTeam":{"id":57,"name":"Arsenal FC","shortName":"Arsenal","tla":"ARS","crest":"https://crests.football-data.org/57.png"},"score":{"winner":null,"duration":"REGULAR","fullTime":{"home":null,"away":null},"halfTime":{"home":null,"away":null}},"odds":{"msg":"Activate Odds-Package in User-Panel to retrieve odds."},"referees":[]},{"area":{"id":2088,"name":"Germany","code":"DEU","flag":"https://crests.football-data.org/759.svg"},"competition":{"id":2002,"name":"Bundesliga","code":"BL1","type":"LEAGUE","emblem":"https://crests.football-data.org/BL1.png"},"season":{"id":2414,"startDate":"2025-08-22","endDate":"2026-05-16","currentMatchday":2,"winner":null},"id":540415,"utcDate":"2025-08-31T15:30:00Z","status":"TIMED","matchday":2,"stage":"REGULAR_SEASON","group":null,"lastUpdated":"2025-08-31T01:32:00Z","homeTeam":{"id":4,"name":"Borussia Dortmund","shortName":"Dortmund","tla":"BVB","crest":"https://crests.football-data.org/4.png"},"awayTeam":{"id":28,"name":"1. FC Union Berlin","shortName":"Union Berlin","tla":"UNB","crest":"https://crests.football-data.org/28.png"},"score":{"winner":null,"duration":"REGULAR","fullTime":{"home":null,"away":null},"halfTime":{"home":null,"away":null}},"odds":{"msg":"Activate Odds-Package in User-Panel to retrieve odds."},"referees":[]},{"area":{"id":2114,"name":"Italy","code":"ITA","flag":"https://crests.football-data.org/784.svg"},"competition":{"id":2019,"name":"Serie A","code":"SA","type":"LEAGUE","emblem":"https://crests.football-data.org/SA.png"},"season":{"id":2395,"startDate":"2025-08-24","endDate":"2026-05-24","currentMatchday":2,"winner":null},"id":536825,"utcDate":"2025-08-31T16:30:00Z","status":"TIMED","matchday":2,"stage":"REGULAR_SEASON","group":null,"lastUpdated":"2025-08-31T01:32:01Z","homeTeam":{"id":107,"name":"Genoa CFC","shortName":"Genoa","tla":"GEN","crest":"https://crests.football-data.org/107.png"},"awayTeam":{"id":109,"name":"Juventus FC","shortName":"Juventus","tla":"JUV","crest":"https://crests.football-data.org/109.png"},"score":{"winner":null,"duration":"REGULAR","fullTime":{"home":null,"away":null},"halfTime":{"home":null,"away":null}},"odds":{"msg":"Activate Odds-Package in User-Panel to retrieve odds."},"referees":[]},{"area":{"id":2114,"name":"Italy","code":"ITA","flag":"https://crests.football-data.org/784.svg"},"competition":{"id":2019,"name":"Serie A","code":"SA","type":"LEAGUE","emblem":"https://crests.football-data.org/SA.png"},"season":{"id":2395,"startDate":"2025-08-24","endDate":"2026-05-24","currentMatchday":2,"winner":null},"id":536827,"utcDate":"2025-08-31T16:30:00Z","status":"TIMED","matchday":2,"stage":"REGULAR_SEASON","group":null,"lastUpdated":"2025-08-31T01:32:01Z","homeTeam":{"id":586,"name":"Torino FC","shortName":"Torino","tla":"TOR","crest":"https://crests.football-data.org/586.png"},"awayTeam":{"id":99,"name":"ACF Fiorentina","shortName":"Fiorentina","tla":"FIO","crest":"https://crests.football-data.org/99.png"},"score":{"winner":null,"duration":"REGULAR","fullTime":{"home":null,"away":null},"halfTime":{"home":null,"away":null}},"odds":{"msg":"Activate Odds-Package in User-Panel to retrieve odds."},"referees":[]},{"area":{"id":2187,"name":"Portugal","code":"POR","flag":"https://crests.football-data.org/765.svg"},"competition":{"id":2017,"name":"Primeira Liga","code":"PPL","type":"LEAGUE","emblem":"https://crests.football-data.org/PPL.png"},"season":{"id":2433,"startDate":"2025-08-08","endDate":"2026-05-17","currentMatchday":4,"winner":null},"id":545729,"utcDate":"2025-08-31T17:00:00Z","status":"TIMED","matchday":4,"stage":"REGULAR_SEASON","group":null,"lastUpdated":"2025-08-31T01:32:01Z","homeTeam":{"id":7822,"name":"FC Alverca","shortName":"Alverca","tla":"ALV","crest":"https://crests.football-data.org/7822.png"},"awayTeam":{"id":1903,"name":"Sport Lisboa e Benfica","shortName":"SL Benfica","tla":"BEN","crest":"https://crests.football-data.org/1903.png"},"score":{"winner":null,"duration":"REGULAR","fullTime":{"home":null,"away":null},"halfTime":{"home":null,"away":null}},"odds":{"msg":"Activate Odds-Package in User-Panel to retrieve odds."},"referees":[]},{"area":{"id":2224,"name":"Spain","code":"ESP","flag":"https://crests.football-data.org/760.svg"},"competition":{"id":2014,"name":"Primera Division","code":"PD","type":"LEAGUE","emblem":"https://crests.football-data.org/laliga.png"},"season":{"id":2429,"startDate":"2025-08-17","endDate":"2026-05-24","currentMatchday":6,"winner":null},"id":544237,"utcDate":"2025-08-31T17:00:00Z","status":"TIMED","matchday":3,"stage":"REGULAR_SEASON","group":null,"lastUpdated":"2025-08-30T01:32:03Z","homeTeam":{"id":90,"name":"Real Betis Balompié","shortName":"Real Betis","tla":"BET","crest":"https://crests.football-data.org/90.png"},"awayTeam":{"id":77,"name":"Athletic Club","shortName":"Athletic","tla":"ATH","crest":"https://crests.football-data.org/77.png"},"score":{"winner":null,"duration":"REGULAR","fullTime":{"home":null,"away":null},"halfTime":{"home":null,"away":null}},"odds":{"msg":"Activate Odds-Package in User-Panel to retrieve odds."},"referees":[]},{"area":{"id":2088,"name":"Germany","code":"DEU","flag":"https://crests.football-data.org/759.svg"},"competition":{"id":2002,"name":"Bundesliga","code":"BL1","type":"LEAGUE","emblem":"https://crests.football-data.org/BL1.png"},"season":{"id":2414,"startDate":"2025-08-22","endDate":"2026-05-16","currentMatchday":2,"winner":null},"id":540422,"utcDate":"2025-08-31T17:30:00Z","status":"TIMED","matchday":2,"stage":"REGULAR_SEASON","group":null,"lastUpdated":"2025-08-31T01:32:01Z","homeTeam":{"id":1,"name":"1. FC Köln","shortName":"1. FC Köln","tla":"KOE","crest":"https://crests.football-data.org/1.png"},"awayTeam":{"id":17,"name":"SC Freiburg","shortName":"Freiburg","tla":"SCF","crest":"https://crests.football-data.org/17.png"},"score":{"winner":null,"duration":"REGULAR","fullTime":{"home":null,"away":null},"halfTime":{"home":null,"away":null}},"odds":{"msg":"Activate Odds-Package in User-Panel to retrieve odds."},"referees":[]},{"area":{"id":2224,"name":"Spain","code":"ESP","flag":"https://crests.football-data.org/760.svg"},"competition":{"id":2014,"name":"Primera Division","code":"PD","type":"LEAGUE","emblem":"https://crests.football-data.org/laliga.png"},"season":{"id":2429,"startDate":"2025-08-17","endDate":"2026-05-24","currentMatchday":6,"winner":null},"id":544234,"utcDate":"2025-08-31T17:30:00Z","status":"TIMED","matchday":3,"stage":"REGULAR_SEASON","group":null,"lastUpdated":"2025-08-31T01:32:01Z","homeTeam":{"id":80,"name":"RCD Espanyol de Barcelona","shortName":"Espanyol","tla":"ESP","crest":"https://crests.football-data.org/80.png"},"awayTeam":{"id":79,"name":"CA Osasuna","shortName":"Osasuna","tla":"OSA","crest":"https://crests.football-data.org/79.png"},"score":{"winner":null,"duration":"REGULAR","fullTime":{"home":null,"away":null},"halfTime":{"home":null,"away":null}},"odds":{"msg":"Activate Odds-Package in User-Panel to retrieve odds."},"referees":[]},{"area":{"id":2072,"name":"England","code":"ENG","flag":"https://crests.football-data.org/770.svg"},"competition":{"id":2021,"name":"Premier League","code":"PL","type":"LEAGUE","emblem":"https://crests.football-data.org/PL.png"},"season":{"id":2403,"startDate":"2025-08-15","endDate":"2026-05-24","currentMatchday":3,"winner":null},"id":537806,"utcDate":"2025-08-31T18:00:00Z","status":"TIMED","matchday":3,"stage":"REGULAR_SEASON","group":null,"lastUpdated":"2025-08-25T01:32:06Z","homeTeam":{"id":58,"name":"Aston Villa FC","shortName":"Aston Villa","tla":"AVL","crest":"https://crests.football-data.org/58.png"},"awayTeam":{"id":354,"name":"Crystal Palace FC","shortName":"Crystal Palace","tla":"CRY","crest":"https://crests.football-data.org/354.png"},"score":{"winner":null,"duration":"REGULAR","fullTime":{"home":null,"away":null},"halfTime":{"home":null,"away":null}},"odds":{"msg":"Activate Odds-Package in User-Panel to retrieve odds."},"referees":[]},{"area":{"id":2081,"name":"France","code":"FRA","flag":"https://crests.football-data.org/773.svg"},"competition":{"id":2015,"name":"Ligue 1","code":"FL1","type":"LEAGUE","emblem":"https://crests.football-data.org/FL1.png"},"season":{"id":2420,"startDate":"2025-08-17","endDate":"2026-05-16","currentMatchday":3,"winner":null},"id":542430,"utcDate":"2025-08-31T18:45:00Z","status":"TIMED","matchday":3,"stage":"REGULAR_SEASON","group":null,"lastUpdated":"2025-08-31T01:32:01Z","homeTeam":{"id":523,"name":"Olympique Lyonnais","shortName":"Olympique Lyon","tla":"LYO","crest":"https://crests.football-data.org/523.png"},"awayTeam":{"id":516,"name":"Olympique de Marseille","shortName":"Marseille","tla":"MAR","crest":"https://crests.football-data.org/516.png"},"score":{"winner":null,"duration":"REGULAR","fullTime":{"home":null,"away":null},"halfTime":{"home":null,"away":null}},"odds":{"msg":"Activate Odds-Package in User-Panel to retrieve odds."},"referees":[]},{"area":{"id":2114,"name":"Italy","code":"ITA","flag":"https://crests.football-data.org/784.svg"},"competition":{"id":2019,"name":"Serie A","code":"SA","type":"LEAGUE","emblem":"https://crests.football-data.org/SA.png"},"season":{"id":2395,"startDate":"2025-08-24","endDate":"2026-05-24","currentMatchday":2,"winner":null},"id":536828,"utcDate":"2025-08-31T18:45:00Z","status":"TIMED","matchday":2,"stage":"REGULAR_SEASON","group":null,"lastUpdated":"2025-08-31T01:32:01Z","homeTeam":{"id":108,"name":"FC Internazionale Milano","shortName":"Inter","tla":"INT","crest":"https://crests.football-data.org/108.png"},"awayTeam":{"id":115,"name":"Udinese Calcio","shortName":"Udinese","tla":"UDI","crest":"https://crests.football-data.org/115.png"},"score":{"winner":null,"duration":"REGULAR","fullTime":{"home":null,"away":null},"halfTime":{"home":null,"away":null}},"odds":{"msg":"Activate Odds-Package in User-Panel to retrieve odds."},"referees":[]},{"area":{"id":2114,"name":"Italy","code":"ITA","flag":"https://crests.football-data.org/784.svg"},"competition":{"id":2019,"name":"Serie A","code":"SA","type":"LEAGUE","emblem":"https://crests.football-data.org/SA.png"},"season":{"id":2395,"startDate":"2025-08-24","endDate":"2026-05-24","currentMatchday":2,"winner":null},"id":536829,"utcDate":"2025-08-31T18:45:00Z","status":"TIMED","matchday":2,"stage":"REGULAR_SEASON","group":null,"lastUpdated":"2025-08-31T01:32:01Z","homeTeam":{"id":110,"name":"SS Lazio","shortName":"Lazio","tla":"LAZ","crest":"https://crests.football-data.org/110.png"},"awayTeam":{"id":450,"name":"Hellas Verona FC","shortName":"Verona","tla":"HVE","crest":"https://crests.football-data.org/450.png"},"score":{"winner":null,"duration":"REGULAR","fullTime":{"home":null,"away":null},"halfTime":{"home":null,"away":null}},"odds":{"msg":"Activate Odds-Package in User-Panel to retrieve odds."},"referees":[]},{"area":{"id":2032,"name":"Brazil","code":"BRA","flag":"https://crests.football-data.org/764.svg"},"competition":{"id":2013,"name":"Campeonato Brasileiro Série A","code":"BSA","type":"LEAGUE","emblem":"https://crests.football-data.org/bsa.png"},"season":{"id":2371,"startDate":"2025-03-29","endDate":"2025-12-21","currentMatchday":22,"winner":null},"id":535145,"utcDate":"2025-08-31T19:00:00Z","status":"TIMED","matchday":22,"stage":"REGULAR_SEASON","group":null,"lastUpdated":"2025-08-30T15:20:47Z","homeTeam":{"id":1783,"name":"CR Flamengo","shortName":"Flamengo","tla":"FLA","crest":"https://crests.football-data.org/1783.png"},"awayTeam":{"id":1767,"name":"Grêmio FBPA","shortName":"Grêmio","tla":"FBP","crest":"https://crests.football-data.org/1767.png"},"score":{"winner":null,"duration":"REGULAR","fullTime":{"home":null,"away":null},"halfTime":{"home":null,"away":null}},"odds":{"msg":"Activate Odds-Package in User-Panel to retrieve odds."},"referees":[]},{"area":{"id":2032,"name":"Brazil","code":"BRA","flag":"https://crests.football-data.org/764.svg"},"competition":{"id":2013,"name":"Campeonato Brasileiro Série A","code":"BSA","type":"LEAGUE","emblem":"https://crests.football-data.org/bsa.png"},"season":{"id":2371,"startDate":"2025-03-29","endDate":"2025-12-21","currentMatchday":22,"winner":null},"id":535148,"utcDate":"2025-08-31T19:00:00Z","status":"TIMED","matchday":22,"stage":"REGULAR_SEASON","group":null,"lastUpdated":"2025-08-25T01:32:06Z","homeTeam":{"id":6685,"name":"Santos FC","shortName":"Santos","tla":"SAN","crest":"https://crests.football-data.org/6685.png"},"awayTeam":{"id":1765,"name":"Fluminense FC","shortName":"Fluminense","tla":"FLU","crest":"https://crests.football-data.org/1765.png"},"score":{"winner":null,"duration":"REGULAR","fullTime":{"home":null,"away":null},"halfTime":{"home":null,"away":null}},"odds":{"msg":"Activate Odds-Package in User-Panel to retrieve odds."},"referees":[]},{"area":{"id":2187,"name":"Portugal","code":"POR","flag":"https://crests.football-data.org/765.svg"},"competition":{"id":2017,"name":"Primeira Liga","code":"PPL","type":"LEAGUE","emblem":"https://crests.football-data.org/PPL.png"},"season":{"id":2433,"startDate":"2025-08-08","endDate":"2026-05-17","currentMatchday":4,"winner":null},"id":545731,"utcDate":"2025-08-31T19:30:00Z","status":"TIMED","matchday":4,"stage":"REGULAR_SEASON","group":null,"lastUpdated":"2025-08-31T01:32:01Z","homeTeam":{"id":5530,"name":"CD Santa Clara","shortName":"Santa Clara","tla":"CD ","crest":"https://crests.football-data.org/5530.png"},"awayTeam":{"id":9136,"name":"CF Estrela da Amadora","shortName":"Amadora","tla":"AMA","crest":"https://crests.football-data.org/9136.png"},"score":{"winner":null,"duration":"REGULAR","fullTime":{"home":null,"away":null},"halfTime":{"home":null,"away":null}},"odds":{"msg":"Activate Odds-Package in User-Panel to retrieve odds."},"referees":[]},{"area":{"id":2187,"name":"Portugal","code":"POR","flag":"https://crests.football-data.org/765.svg"},"competition":{"id":2017,"name":"Primeira Liga","code":"PPL","type":"LEAGUE","emblem":"https://crests.football-data.org/PPL.png"},"season":{"id":2433,"startDate":"2025-08-08","endDate":"2026-05-17","currentMatchday":4,"winner":null},"id":545735,"utcDate":"2025-08-31T19:30:00Z","status":"TIMED","matchday":4,"stage":"REGULAR_SEASON","group":null,"lastUpdated":"2025-08-31T01:32:01Z","homeTeam":{"id":496,"name":"Rio Ave FC","shortName":"Rio Ave","tla":"RIO","crest":"https://crests.football-data.org/496.png"},"awayTeam":{"id":5613,"name":"Sporting Clube de Braga","shortName":"Braga","tla":"SCB","crest":"https://crests.football-data.org/5613.png"},"score":{"winner":null,"duration":"REGULAR","fullTime":{"home":null,"away":null},"halfTime":{"home":null,"away":null}},"odds":{"msg":"Activate Odds-Package in User-Panel to retrieve odds."},"referees":[]},{"area":{"id":2224,"name":"Spain","code":"ESP","flag":"https://crests.football-data.org/760.svg"},"competition":{"id":2014,"name":"Primera Division","code":"PD","type":"LEAGUE","emblem":"https://crests.football-data.org/laliga.png"},"season":{"id":2429,"startDate":"2025-08-17","endDate":"2026-05-24","currentMatchday":6,"winner":null},"id":544238,"utcDate":"2025-08-31T19:30:00Z","status":"TIMED","matchday":3,"stage":"REGULAR_SEASON","group":null,"lastUpdated":"2025-08-31T01:32:01Z","homeTeam":{"id":87,"name":"Rayo Vallecano de Madrid","shortName":"Rayo Vallecano","tla":"RAY","crest":"https://crests.football-data.org/87.png"},"awayTeam":{"id":81,"name":"FC Barcelona","shortName":"Barça","tla":"FCB","crest":"https://crests.football-data.org/81.png"},"score":{"winner":null,"duration":"REGULAR","fullTime":{"home":null,"away":null},"halfTime":{"home":null,"away":null}},"odds":{"msg":"Activate Odds-Package in User-Panel to retrieve odds."},"referees":[]},{"area":{"id":2032,"name":"Brazil","code":"BRA","flag":"https://crests.football-data.org/764.svg"},"competition":{"id":2013,"name":"Campeonato Brasileiro Série A","code":"BSA","type":"LEAGUE","emblem":"https://crests.football-data.org/bsa.png"},"season":{"id":2371,"startDate":"2025-03-29","endDate":"2025-12-21","currentMatchday":22,"winner":null},"id":535147,"utcDate":"2025-08-31T21:30:00Z","status":"TIMED","matchday":22,"stage":"REGULAR_SEASON","group":null,"lastUpdated":"2025-08-30T15:20:47Z","homeTeam":{"id":1779,"name":"SC Corinthians Paulista","shortName":"Corinthians","tla":"COR","crest":"https://crests.football-data.org/1779.png"},"awayTeam":{"id":1769,"name":"SE Palmeiras","shortName":"Palmeiras","tla":"PAL","crest":"https://crests.football-data.org/1769.png"},"score":{"winner":null,"duration":"REGULAR","fullTime":{"home":null,"away":null},"halfTime":{"home":null,"away":null}},"odds":{"msg":"Activate Odds-Package in User-Panel to retrieve odds."},"referees":[]},{"area":{"id":2032,"name":"Brazil","code":"BRA","flag":"https://crests.football-data.org/764.svg"},"competition":{"id":2013,"name":"Campeonato Brasileiro Série A","code":"BSA","type":"LEAGUE","emblem":"https://crests.football-data.org/bsa.png"},"season":{"id":2371,"startDate":"2025-03-29","endDate":"2025-12-21","currentMatchday":22,"winner":null},"id":535149,"utcDate":"2025-08-31T21:30:00Z","status":"TIMED","matchday":22,"stage":"REGULAR_SEASON","group":null,"lastUpdated":"2025-08-25T01:32:06Z","homeTeam":{"id":4364,"name":"Mirassol FC","shortName":"Mirassol","tla":"MIR","crest":"https://crests.football-data.org/4364.png"},"awayTeam":{"id":1777,"name":"EC Bahia","shortName":"Bahia","tla":"BAH","crest":"https://crests.football-data.org/1777.png"},"score":{"winner":null,"duration":"REGULAR","fullTime":{"home":null,"away":null},"halfTime":{"home":null,"away":null}},"odds":{"msg":"Activate Odds-Package in User-Panel to retrieve odds."},"referees":[]},{"area":{"id":2032,"name":"Brazil","code":"BRA","flag":"https://crests.football-data.org/764.svg"},"competition":{"id":2013,"name":"Campeonato Brasileiro Série A","code":"BSA","type":"LEAGUE","emblem":"https://crests.football-data.org/bsa.png"},"season":{"id":2371,"startDate":"2025-03-29","endDate":"2025-12-21","currentMatchday":22,"winner":null},"id":535152,"utcDate":"2025-08-31T21:30:00Z","status":"TIMED","matchday":22,"stage":"REGULAR_SEASON","group":null,"lastUpdated":"2025-08-31T01:32:01Z","homeTeam":{"id":1782,"name":"EC Vitória","shortName":"Vitória","tla":"VIT","crest":"https://crests.football-data.org/1782.png"},"awayTeam":{"id":1766,"name":"CA Mineiro","shortName":"Mineiro","tla":"CAM","crest":"https://crests.football-data.org/1766.png"},"score":{"winner":null,"duration":"REGULAR","fullTime":{"home":null,"away":null},"halfTime":{"home":null,"away":null}},"odds":{"msg":"Activate Odds-Package in User-Panel to retrieve odds."},"referees":[]},{"area":{"id":2032,"name":"Brazil","code":"BRA","flag":"https://crests.football-data.org/764.svg"},"competition":{"id":2013,"name":"Campeonato Brasileiro Série A","code":"BSA","type":"LEAGUE","emblem":"https://crests.football-data.org/bsa.png"},"season":{"id":2371,"startDate":"2025-03-29","endDate":"2025-12-21","currentMatchday":22,"winner":null},"id":535151,"utcDate":"2025-08-31T23:30:00Z","status":"TIMED","matchday":22,"stage":"REGULAR_SEASON","group":null,"lastUpdated":"2025-08-25T01:32:06Z","homeTeam":{"id":6684,"name":"SC Internacional","shortName":"Internacional","tla":"SCI","crest":"https://crests.football-data.org/6684.png"},"awayTeam":{"id":3984,"name":"Fortaleza EC","shortName":"Fortaleza","tla":"FEC","crest":"https://crests.football-data.org/3984.png"},"score":{"winner":null,"duration":"REGULAR","fullTime":{"home":null,"away":null},"halfTime":{"home":null,"away":null}},"odds":{"msg":"Activate Odds-Package in User-Panel to retrieve odds."},"referees":[]},{"area":{"id":2032,"name":"Brazil","code":"BRA","flag":"https://crests.football-data.org/764.svg"},"competition":{"id":2013,"name":"Campeonato Brasileiro Série A","code":"BSA","type":"LEAGUE","emblem":"https://crests.football-data.org/bsa.png"},"season":{"id":2371,"startDate":"2025-03-29","endDate":"2025-12-21","currentMatchday":22,"winner":null},"id":535154,"utcDate":"2025-08-31T23:30:00Z","status":"TIMED","matchday":22,"stage":"REGULAR_SEASON","group":null,"lastUpdated":"2025-08-31T01:32:01Z","homeTeam":{"id":1778,"name":"SC Recife","shortName":"Recife","tla":"REC","crest":"https://crests.football-data.org/1778.png"},"awayTeam":{"id":1780,"name":"CR Vasco da Gama","shortName":"Vasco da Gama","tla":"VAS","crest":"https://crests.football-data.org/1780.png"},"score":{"winner":null,"duration":"REGULAR","fullTime":{"home":null,"away":null},"halfTime":{"home":null,"away":null}},"odds":{"msg":"Activate Odds-Package in User-Panel to retrieve odds."},"referees":[]}]}