{"filters":{"dateFrom":"2025-09-25","dateTo":"2025-09-26","permission":"TIER_ONE"},"resultSet":{"count":4,"competitions":"CLI,PD","first":"2025-09-25","last":"2025-09-25","played":0},"matches":[{"area":{"id":2220,"name":"South America","code":"SAM","flag":"https://crests.football-data.org/CLI.svg"},"competition":{"id":2152,"name":"Copa Libertadores","code":"CLI","type":"CUP","emblem":"https://crests.football-data.org/CLI.svg"},"season":{"id":2366,"startDate":"2025-02-05","endDate":"2025-11-29","currentMatchday":6,"winner":null},"id":551890,"utcDate":"2025-09-25T00:30:00Z","status":"TIMED","matchday":2,"stage":"QUARTER_FINALS","group":null,"lastUpdated":"2025-09-25T00:21:01Z","homeTeam":{"id":1769,"name":"SE Palmeiras","shortName":"Palmeiras","tla":"PAL","crest":"https://crests.football-data.org/1769.png"},"awayTeam":{"id":6667,"name":"CA River Plate","shortName":"River Plate","tla":"RIV","crest":"https://crests.football-data.org/6667.png"},"score":{"winner":null,"duration":"REGULAR","fullTime":{"home":null,"away":null},"halfTime":{"home":null,"away":null}},"odds":{"msg":"Activate Odds-Package in User-Panel to retrieve odds."},"referees":[]},{"area":{"id":2224,"name":"Spain","code":"ESP","flag":"https://crests.football-data.org/760.svg"},"competition":{"id":2014,"name":"Primera Division","code":"PD","type":"LEAGUE","emblem":"https://crests.football-data.org/laliga.png"},"season":{"id":2429,"startDate":"2025-08-17","endDate":"2026-05-24","currentMatchday":6,"winner":null},"id":544269,"utcDate":"2025-09-25T17:30:00Z","status":"TIMED","matchday":6,"stage":"REGULAR_SEASON","group":null,"lastUpdated":"2025-09-25T01:32:00Z","homeTeam":{"id":79,"name":"CA Osasuna","shortName":"Osasuna","tla":"OSA","crest":"https://crests.football-data.org/79.png"},"awayTeam":{"id":285,"name":"Elche CF","shortName":"Elche","tla":"ELC","crest":"https://crests.football-data.org/285.png"},"score":{"winner":null,"duration":"REGULAR","fullTime":{"home":null,"away":null},"halfTime":{"home":null,"away":null}},"odds":{"msg":"Activate Odds-Package in User-Panel to retrieve odds."},"referees":[]},{"area":{"id":2224,"name":"Spain","code":"ESP","flag":"https://crests.football-data.org/760.svg"},"competition":{"id":2014,"name":"Primera Division","code":"PD","type":"LEAGUE","emblem":"https://crests.football-data.org/laliga.png"},"season":{"id":2429,"startDate":"2025-08-17","endDate":"2026-05-24","currentMatchday":6,"winner":null},"id":544267,"utcDate":"2025-09-25T19:30:00Z","status":"TIMED","matchday":6,"stage":"REGULAR_SEASON","group":null,"lastUpdated":"2025-09-25T01:32:00Z","homeTeam":{"id":1048,"name":"Real Oviedo","shortName":"Real Oviedo","tla":"OVI","crest":"https://crests.football-data.org/1048.png"},"awayTeam":{"id":81,"name":"FC Barcelona","shortName":"Barça","tla":"FCB","crest":"https://crests.football-data.org/81.png"},"score":{"winner":null,"duration":"REGULAR","fullTime":{"home":null,"away":null},"halfTime":{"home":null,"away":null}},"odds":{"msg":"Activate Odds-Package in User-Panel to retrieve odds."},"referees":[]},{"area":{"id":2220,"name":"South America","code":"SAM","flag":"https://crests.football-data.org/CLI.svg"},"competition":{"id":2152,"name":"Copa Libertadores","code":"CLI","type":"CUP","emblem":"https://crests.football-data.org/CLI.svg"},"season":{"id":2366,"startDate":"2025-02-05","endDate":"2025-11-29","currentMatchday":6,"winner":null},"id":551889,"utcDate":"2025-09-25T22:00:00Z","status":"TIMED","matchday":2,"stage":"QUARTER_FINALS","group":null,"lastUpdated":"2025-08-29T00:20:56Z","homeTeam":{"id":1776,"name":"São Paulo FC","shortName":"São Paulo","tla":"PAU","crest":"https://crests.football-data.org/1776.png"},"awayTeam":{"id":4528,"name":"LDU de Quito","shortName":"LDU de Quito","tla":"LDU","crest":"https://crests.football-data.org/4528.png"},"score":{"winner":null,"duration":"REGULAR","fullTime":{"home":null,"away":null},"halfTime":{"home":null,"away":null}},"odds":{"msg":"Activate Odds-Package in User-Panel to retrieve odds."},"referees":[]}]}