{"filters":{"dateFrom":"2026-04-16","dateTo":"2026-04-17","permission":"TIER_ONE"},"resultSet":{"count":5,"competitions":"CLI","first":"2026-04-16","last":"2026-04-16","played":0},"matches":[{"area":{"id":2220,"name":"South America","code":"SAM","flag":"https://crests.football-data.org/CLI.svg"},"competition":{"id":2152,"name":"Copa Libertadores","code":"CLI","type":"CUP","emblem":"https://crests.football-data.org/CLI.svg"},"season":{"id":2466,"startDate":"2026-02-04","endDate":"2026-11-28","currentMatchday":2,"winner":null},"id":557134,"utcDate":"2026-04-16T00:30:00Z","status":"IN_PLAY","matchday":2,"stage":"GROUP_STAGE","group":"GROUP_E","lastUpdated":"2026-04-16T02:59:57Z","homeTeam":{"id":1779,"name":"SC Corinthians Paulista","shortName":"Corinthians","tla":"COR","crest":"https://crests.football-data.org/1779.png"},"awayTeam":{"id":4441,"name":"Independiente Santa Fe","shortName":"Santa Fe","tla":"SAN","crest":"https://crests.football-data.org/4441.png"},"score":{"winner":"DRAW","duration":"REGULAR","fullTime":{"home":0,"away":0},"halfTime":{"home":null,"away":null}},"odds":{"msg":"Activate Odds-Package in User-Panel to retrieve odds."},"referees":[{"id":116383,"name":"Juan Benítez","type":"REFEREE","nationality":"Paraguay"}]},{"area":{"id":2220,"name":"South America","code":"SAM","flag":"https://crests.football-data.org/CLI.svg"},"competition":{"id":2152,"name":"Copa Libertadores","code":"CLI","type":"CUP","emblem":"https://crests.football-data.org/CLI.svg"},"season":{"id":2466,"startDate":"2026-02-04","endDate":"2026-11-28","currentMatchday":2,"winner":null},"id":557111,"utcDate":"2026-04-16T00:30:00Z","status":"IN_PLAY","matchday":2,"stage":"GROUP_STAGE","group":"GROUP_C","lastUpdated":"2026-04-16T03:00:01Z","homeTeam":{"id":1765,"name":"Fluminense FC","shortName":"Fluminense","tla":"FLU","crest":"https://crests.football-data.org/1765.png"},"awayTeam":{"id":2052,"name":"CS Independiente Rivadavia","shortName":"Rivadavia","tla":"RIV","crest":"https://crests.football-data.org/2052.png"},"score":{"winner":"HOME_TEAM","duration":"REGULAR","fullTime":{"home":1,"away":0},"halfTime":{"home":null,"away":null}},"odds":{"msg":"Activate Odds-Package in User-Panel to retrieve odds."},"referees":[{"id":182493,"name":"John Ospina","type":"REFEREE","nationality":"Colombia"}]},{"area":{"id":2220,"name":"South America","code":"SAM","flag":"https://crests.football-data.org/CLI.svg"},"competition":{"id":2152,"name":"Copa Libertadores","code":"CLI","type":"CUP","emblem":"https://crests.football-data.org/CLI.svg"},"season":{"id":2466,"startDate":"2026-02-04","endDate":"2026-11-28","currentMatchday":2,"winner":null},"id":557171,"utcDate":"2026-04-16T02:00:00Z","status":"TIMED","matchday":2,"stage":"GROUP_STAGE","group":"GROUP_H","lastUpdated":"2026-04-16T02:53:07Z","homeTeam":{"id":6989,"name":"CAR Independiente del Valle","shortName":"Independiente","tla":"IDL","crest":"https://crests.football-data.org/6989.png"},"awayTeam":{"id":9357,"name":"Universidad Central de Venezuela FC","shortName":null,"tla":"","crest":"https://crests.football-data.org/9357.png"},"score":{"winner":null,"duration":"REGULAR","fullTime":{"home":null,"away":null},"halfTime":{"home":null,"away":null}},"odds":{"msg":"Activate Odds-Package in User-Panel to retrieve odds."},"referees":[{"id":221505,"name":"Jordi Espinoza","type":"REFEREE","nationality":"Peru"}]},{"area":{"id":2220,"name":"South America","code":"SAM","flag":"https://crests.football-data.org/CLI.svg"},"competition":{"id":2152,"name":"Copa Libertadores","code":"CLI","type":"CUP","emblem":"https://crests.football-data.org/CLI.svg"},"season":{"id":2466,"startDate":"2026-02-04","endDate":"2026-11-28","currentMatchday":2,"winner":null},"id":557158,"utcDate":"2026-04-16T22:00:00Z","status":"TIMED","matchday":2,"stage":"GROUP_STAGE","group":"GROUP_G","lastUpdated":"2026-03-23T03:59:22Z","homeTeam":{"id":2066,"name":"CA Lanús","shortName":"Lanús","tla":"LAN","crest":"https://crests.football-data.org/2066.png"},"awayTeam":{"id":7865,"name":"Club Always Ready","shortName":"Always Ready","tla":"CAR","crest":"https://crests.football-data.org/7865.png"},"score":{"winner":null,"duration":"REGULAR","fullTime":{"home":null,"away":null},"halfTime":{"home":null,"away":null}},"odds":{"msg":"Activate Odds-Package in User-Panel to retrieve odds."},"referees":[]},{"area":{"id":2220,"name":"South America","code":"SAM","flag":"https://crests.football-data.org/CLI.svg"},"competition":{"id":2152,"name":"Copa Libertadores","code":"CLI","type":"CUP","emblem":"https://crests.football-data.org/CLI.svg"},"season":{"id":2466,"startDate":"2026-02-04","endDate":"2026-11-28","currentMatchday":2,"winner":null},"id":557147,"utcDate":"2026-04-16T22:00:00Z","status":"TIMED","matchday":2,"stage":"GROUP_STAGE","group":"GROUP_F","lastUpdated":"2026-04-15T20:21:13Z","homeTeam":{"id":1769,"name":"SE Palmeiras","shortName":"Palmeiras","tla":"PAL","crest":"https://crests.football-data.org/1769.png"},"awayTeam":{"id":5347,"name":"CS Cristal","shortName":"Cristal","tla":"SPO","crest":"https://crests.football-data.org/5347.png"},"score":{"winner":null,"duration":"REGULAR","fullTime":{"home":null,"away":null},"halfTime":{"home":null,"away":null}},"odds":{"msg":"Activate Odds-Package in User-Panel to retrieve odds."},"referees":[]}]}